pypermissive/__init__.py
pypermissive/base_model.py
pypermissive/decorators.py
pypermissive/field.py
pypermissive-1.1.3.dist-info/LICENSE
pypermissive-1.1.3.dist-info/METADATA
pypermissive-1.1.3.dist-info/WHEEL
pypermissive-1.1.3.dist-info/RECORD
