Metadata-Version: 2.3
Name: pypermissive
Version: 1.1.3
Summary: Validation library
Home-page: https://github.com/kaliv0/pypermissive
License: LICENSE
Keywords: validation library,type validator
Author: kaliv0
Author-email: kaloyan.ivanov88@gmail.com
Requires-Python: >=3.12,<4.0
Classifier: License :: Other/Proprietary License
Classifier: Programming Language :: Python :: 3
Classifier: Programming Language :: Python :: 3.12
Classifier: Programming Language :: Python :: 3.13
Project-URL: Repository, https://github.com/kaliv0/pypermissive
